rapidfuzz_capi/__init__.pxd
rapidfuzz_capi/__init__.py
rapidfuzz_capi/rapidfuzz_capi.h
rapidfuzz_capi-1.0.5.dist-info/LICENSE
rapidfuzz_capi-1.0.5.dist-info/METADATA
rapidfuzz_capi-1.0.5.dist-info/WHEEL
rapidfuzz_capi-1.0.5.dist-info/top_level.txt
rapidfuzz_capi-1.0.5.dist-info/zip-safe
rapidfuzz_capi-1.0.5.dist-info/RECORD
