Metadata-Version: 2.1
Name: rapidfuzz-capi
Version: 1.0.5
Summary: C-API of RapidFuzz, which can be used to extend RapidFuzz from separate packages
Home-page: https://github.com/maxbachmann/rapidfuzz_capi
Author: Max Bachmann
Author-email: pypi@maxbachmann.de
License: MIT
Platform: UNKNOWN
Classifier: Programming Language :: C
Classifier: Programming Language :: C++
Classifier: Programming Language :: Fortran
Classifier: Programming Language :: Python
Classifier: Operating System :: OS Independent
Classifier: Development Status :: 5 - Production/Stable
Classifier: Intended Audience :: Developers
Classifier: Topic :: Software Development :: Build Tools
License-File: LICENSE
